{
  "headers": {
    "expect-ct": "max-age=604800, report-uri=\"https://report-uri.cloudflare.com/cdn-cgi/beacon/expect-ct\"",
    "x-amz-version-id": "yHwmonxLDkCN8dkovzC.KW2FB9wOK99m",
    "vary": "Accept-Encoding",
    "cache-control": "public, max-age=31536000, immutable",
    "x-amz-id-2": "UB6oRdR0dChJ+ewQtojczzn35LCXebCrLS1bLQ4rKNUgCiLqopZQslmiJOabt2ev1DE7kmNlQno=",
    "server": "cloudflare",
    "content-type": "application/typescript; charset=utf-8",
    "access-control-allow-origin": "*",
    "cf-ray": "656845614c6b5a51-IAD",
    "cf-cache-status": "MISS",
    "content-length": "1879",
    "accept-ranges": "bytes",
    "last-modified": "Tue, 13 Apr 2021 18:10:49 GMT",
    "cf-request-id": "0a5509b0d900005a5162b16000000001",
    "alt-svc": "h3-27=\":443\"; ma=86400, h3-28=\":443\"; ma=86400, h3-29=\":443\"; ma=86400",
    "etag": "\"426eb73199e9f65d6b2fb48816843fb7\"",
    "date": "Fri, 28 May 2021 14:46:11 GMT",
    "x-amz-request-id": "KCFQQZWH5GBPD4CN"
  },
  "url": "https://deno.land/std@0.93.0/node/_fs/_fs_readlink.ts"
}