{
  "headers": {
    "etag": "\"d8348e3d9cf4785feed19c6088c3a38e\"",
    "last-modified": "Mon, 23 Nov 2020 14:12:13 GMT",
    "cache-control": "public, max-age=31536000, immutable",
    "accept-ranges": "bytes",
    "cf-ray": "65684563984c5a51-IAD",
    "content-type": "application/typescript; charset=utf-8",
    "x-amz-version-id": "bm0OWqqowSLEpMZA63Owcq4phNLXrfVv",
    "expect-ct": "max-age=604800, report-uri=\"https://report-uri.cloudflare.com/cdn-cgi/beacon/expect-ct\"",
    "x-amz-id-2": "/gGimXZiFLhBDUmYcS4P4qtq4VNJyIT+q4igC7Ah3La5i2Ew4Pw1zuK2ysRRLvpNasRtdx1UDGA=",
    "vary": "Accept-Encoding",
    "server": "cloudflare",
    "content-length": "3172",
    "date": "Fri, 28 May 2021 14:46:11 GMT",
    "alt-svc": "h3-27=\":443\"; ma=86400, h3-28=\":443\"; ma=86400, h3-29=\":443\"; ma=86400",
    "access-control-allow-origin": "*",
    "cf-request-id": "0a5509b24000005a5162b3e000000001",
    "x-amz-request-id": "KCFSPJ72F76WGZNF",
    "cf-cache-status": "EXPIRED"
  },
  "url": "https://deno.land/std@0.79.0/encoding/hex.ts"
}