{
  "headers": {
    "alt-svc": "h3-27=\":443\"; ma=86400, h3-28=\":443\"; ma=86400, h3-29=\":443\"; ma=86400, h3=\":443\"; ma=86400",
    "expect-ct": "max-age=604800, report-uri=\"https://report-uri.cloudflare.com/cdn-cgi/beacon/expect-ct\"",
    "last-modified": "Thu, 27 May 2021 18:29:50 GMT",
    "x-amz-id-2": "Rd05rnPYPjqACCzzS1HKjFpcrSe3bJwqHFQc5nnz/ejKNStQ/TPA9WEgQ+7/Jwqc9AdkJkQWdxY=",
    "age": "69804",
    "access-control-allow-origin": "*",
    "date": "Mon, 14 Jun 2021 17:15:18 GMT",
    "content-type": "application/typescript; charset=utf-8",
    "x-amz-version-id": "CKh2ICI6QOkzfP7leW03JFlm5wQICTXv",
    "accept-ranges": "bytes",
    "cf-ray": "65f533322a9fe10e-IAD",
    "content-length": "667",
    "cache-control": "public, max-age=31536000, immutable",
    "x-amz-request-id": "P7J19K7GAFXG9WJ3",
    "cf-request-id": "0aad1e53610000e10ef18b0000000001",
    "cf-cache-status": "HIT",
    "etag": "\"8c7ea8ec5f06809d27917edef40db04d\"",
    "vary": "Accept-Encoding",
    "server": "cloudflare"
  },
  "url": "https://deno.land/x/aws_sdk@v3.17.0-2/querystring-builder/mod.ts"
}