{
  "headers": {
    "expect-ct": "max-age=604800, report-uri=\"https://report-uri.cloudflare.com/cdn-cgi/beacon/expect-ct\"",
    "alt-svc": "h3-27=\":443\"; ma=86400, h3-28=\":443\"; ma=86400, h3-29=\":443\"; ma=86400",
    "content-type": "application/typescript; charset=utf-8",
    "date": "Fri, 28 May 2021 14:46:11 GMT",
    "cache-control": "public, max-age=31536000, immutable",
    "x-amz-version-id": "NOvWQ6WCXWKOZWl6bqsSntOt6E2hmw44",
    "cf-request-id": "0a5509af8b00005a51b49c0000000001",
    "etag": "\"93422bd25149e8ee424e3debf3078c7c\"",
    "access-control-allow-origin": "*",
    "vary": "Accept-Encoding",
    "cf-cache-status": "MISS",
    "accept-ranges": "bytes",
    "x-amz-id-2": "B2glDWbU6yKvLq9GPjPDfxpuy7Gp+UEK/pW1v/3h1zR9Bx7mtCm26PM3ploye3VkT8F1mCFaAM4=",
    "content-length": "2918",
    "cf-ray": "6568455f383e5a51-IAD",
    "last-modified": "Mon, 24 May 2021 18:55:08 GMT",
    "server": "cloudflare",
    "x-amz-request-id": "KCFNR2M9RT7N03S1"
  },
  "url": "https://deno.land/x/aws_sdk@v3.16.0-3/smithy-client/client.ts"
}