{
  "headers": {
    "date": "Fri, 04 Jun 2021 22:55:03 GMT",
    "cf-cache-status": "MISS",
    "x-amz-id-2": "UeGPCeMZQYxoNaPqokOu++lyohK/JPMenBGQeV/6rzBH5JoSeclJCHcwEd5O39d+fiVExqTbznE=",
    "vary": "Accept-Encoding",
    "accept-ranges": "bytes",
    "content-length": "1193",
    "cf-ray": "65a4bf204a5b060e-IAD",
    "expect-ct": "max-age=604800, report-uri=\"https://report-uri.cloudflare.com/cdn-cgi/beacon/expect-ct\"",
    "x-amz-version-id": "0eQNxvhWmeOc24_eYlcFl5gtryxcE6di",
    "access-control-allow-origin": "*",
    "alt-svc": "h3-27=\":443\"; ma=86400, h3-28=\":443\"; ma=86400, h3-29=\":443\"; ma=86400, h3=\":443\"; ma=86400",
    "content-type": "application/typescript; charset=utf-8",
    "last-modified": "Mon, 24 May 2021 18:55:08 GMT",
    "cf-request-id": "0a7ad5c82c0000060eeb0b9000000001",
    "x-amz-request-id": "BPZAMFNN6M0CN9RV",
    "server": "cloudflare",
    "cache-control": "public, max-age=31536000, immutable",
    "etag": "\"9a2c531fba78d3ff640fe68437acebf0\""
  },
  "url": "https://deno.land/x/aws_sdk@v3.16.0-3/node-config-provider/configLoader.ts"
}