{
  "headers": {
    "vary": "Accept-Encoding",
    "date": "Fri, 28 May 2021 14:46:11 GMT",
    "access-control-allow-origin": "*",
    "x-amz-id-2": "WDsX2j3NIHYijw65dEqHeWvLrCA+2oYBoxIevxAkGzlWUoKCmy0C787dSOTawoDNKpAAm5lZ/xg=",
    "last-modified": "Mon, 24 May 2021 18:55:08 GMT",
    "alt-svc": "h3-27=\":443\"; ma=86400, h3-28=\":443\"; ma=86400, h3-29=\":443\"; ma=86400",
    "x-amz-version-id": "0sEtMTHx67XHri20C.r6s9zcs3qcPA8g",
    "etag": "\"c9f755b26e77ba51b081b825af6d8e00\"",
    "cf-ray": "656845608add5a51-IAD",
    "accept-ranges": "bytes",
    "expect-ct": "max-age=604800, report-uri=\"https://report-uri.cloudflare.com/cdn-cgi/beacon/expect-ct\"",
    "content-length": "753",
    "content-type": "application/typescript; charset=utf-8",
    "cf-cache-status": "MISS",
    "cache-control": "public, max-age=31536000, immutable",
    "cf-request-id": "0a5509b05a00005a51c933c000000001",
    "x-amz-request-id": "KCFNW61P2BJFK5V6",
    "server": "cloudflare"
  },
  "url": "https://deno.land/x/aws_sdk@v3.16.0-3/service-error-classification/mod.ts"
}