{
  "headers": {
    "x-amz-request-id": "ND16S26X9WMJ8WMG",
    "access-control-allow-origin": "*",
    "content-type": "application/javascript",
    "x-amz-id-2": "qpYdJru1z7gz1o2wG2vuuq3t1dGz0zddmdIkdnR9AVIQpg1oshvH0jto6gusHjkVl6ks+whDozA=",
    "date": "Fri, 01 Apr 2022 16:07:17 GMT",
    "cache-control": "public, max-age=31536000, immutable",
    "last-modified": "Thu, 31 Mar 2022 15:56:33 GMT",
    "server": "deploy/us-east4-c",
    "content-length": "11837",
    "x-amz-version-id": "1_61SNAcZD9Zist6xcclByMeSV1iIg.q",
    "etag": "\"20d5a7dc1b03988764140d4461127699\""
  },
  "url": "https://deno.land/std@0.133.0/_wasm_crypto/crypto.mjs",
  "now": {
    "secs_since_epoch": 1648829236,
    "nanos_since_epoch": 125332000
  }
}