{
  "headers": {
    "cf-request-id": "09d55de3de00003e1cb51fc000000001",
    "expect-ct": "max-age=604800, report-uri=\"https://report-uri.cloudflare.com/cdn-cgi/beacon/expect-ct\"",
    "x-amz-request-id": "JS4F0C9613PJG4N3",
    "date": "Mon, 03 May 2021 19:46:45 GMT",
    "content-length": "1359",
    "last-modified": "Tue, 13 Apr 2021 22:55:01 GMT",
    "cache-control": "public, max-age=31536000, immutable",
    "access-control-allow-origin": "*",
    "vary": "Accept-Encoding",
    "set-cookie": "__cfduid=d594db55f8a6d1506763ce85fd686d2bb1620071205; expires=Wed, 02-Jun-21 19:46:45 GMT; path=/; domain=.deno.land; HttpOnly; SameSite=Lax; Secure",
    "cf-cache-status": "HIT",
    "x-amz-id-2": "rLRy/wF2bS7O0eMQ0s0scehTfwxHXahLFLrMI7q8XUBQGSX5ROuKICMGXkSy+A7zHw4kkB5Yo1U=",
    "cf-ray": "649bff4c9bb63e1c-EWR",
    "age": "371427",
    "content-type": "application/typescript; charset=utf-8",
    "x-amz-version-id": "aRIt__gvtp4XJX1QWzKOCaNxRMd4yopc",
    "server": "cloudflare",
    "alt-svc": "h3-27=\":443\"; ma=86400, h3-28=\":443\"; ma=86400, h3-29=\":443\"; ma=86400",
    "etag": "\"f63b1129dad5afe86f0c730e1a55719f\"",
    "accept-ranges": "bytes"
  },
  "url": "https://deno.land/x/cliffy@v0.18.2/flags/normalize.ts"
}