{
  "headers": {
    "server": "cloudflare",
    "etag": "\"c3bcda669e4c3db76a6d66694226e9b4\"",
    "content-length": "865",
    "access-control-allow-origin": "*",
    "cf-ray": "690d878bfc52e0fe-IAD",
    "x-amz-request-id": "76G5ZGQ5BJC771QA",
    "expect-ct": "max-age=604800, report-uri=\"https://report-uri.cloudflare.com/cdn-cgi/beacon/expect-ct\"",
    "connection": "keep-alive",
    "last-modified": "Mon, 12 Jul 2021 23:47:14 GMT",
    "cf-cache-status": "DYNAMIC",
    "alt-svc": "h3=\":443\"; ma=86400, h3-29=\":443\"; ma=86400, h3-28=\":443\"; ma=86400, h3-27=\":443\"; ma=86400",
    "date": "Sat, 18 Sep 2021 21:04:55 GMT",
    "content-type": "application/typescript; charset=utf-8",
    "x-amz-version-id": "yFhNsM.mQC0gYa.gqyUrtTfx0aXBn7qt",
    "x-amz-id-2": "oFb7sgLGQFa1sukPYSE5jPTMwtOtoj0J7sW797k9wi9ecTRA4PzCSkuMTciWSGCfTTiNPxPpSjk=",
    "cache-control": "public, max-age=31536000, immutable"
  },
  "url": "https://deno.land/std@0.101.0/node/_fs/promises/_fs_readFile.ts"
}