{
  "headers": {
    "x-amz-version-id": "Imo0wDyDD6mtckZdFPy2rk1V33NRe7I1",
    "age": "99138",
    "access-control-allow-origin": "*",
    "cf-cache-status": "HIT",
    "cf-request-id": "09bb094ddd00004be2dc172000000001",
    "x-amz-id-2": "ayPnV5JAYAFOFmmFg4AwJ0p/xCspYhw8dZYEGhE2KIJkGFqnISlyE4dbefKdjdnTaH/TL/OPt70=",
    "cf-ray": "6471de5c993f4be2-AMS",
    "vary": "Accept-Encoding",
    "etag": "\"6aed06fad21dbfdf2624d466685703de\"",
    "expect-ct": "max-age=604800, report-uri=\"https://report-uri.cloudflare.com/cdn-cgi/beacon/expect-ct\"",
    "content-length": "5212",
    "content-type": "application/typescript; charset=utf-8",
    "cache-control": "public, max-age=31536000, immutable",
    "last-modified": "Tue, 13 Apr 2021 22:55:01 GMT",
    "x-amz-request-id": "NBF6NA5PQNHJS9SN",
    "server": "cloudflare",
    "date": "Wed, 28 Apr 2021 17:04:14 GMT",
    "set-cookie": "__cfduid=dc2dabf988a692e452267455265e8c6101619629454; expires=Fri, 28-May-21 17:04:14 GMT; path=/; domain=.deno.land; HttpOnly; SameSite=Lax; Secure",
    "alt-svc": "h3-27=\":443\"; ma=86400, h3-28=\":443\"; ma=86400, h3-29=\":443\"; ma=86400",
    "accept-ranges": "bytes"
  },
  "url": "https://deno.land/x/cliffy@v0.18.2/command/completions/_bash_completions_generator.ts"
}