{
  "headers": {
    "content-length": "34",
    "access-control-allow-origin": "*",
    "last-modified": "Sat, 23 Jan 2021 01:23:53 GMT",
    "x-amz-request-id": "BSFV7QRDW0C23BHM",
    "server": "cloudflare",
    "set-cookie": "__cfduid=d6534d7d12543c4df8da68c4650e177f81619389227; expires=Tue, 25-May-21 22:20:27 GMT; path=/; domain=.deno.land; HttpOnly; SameSite=Lax; Secure",
    "accept-ranges": "bytes",
    "expect-ct": "max-age=604800, report-uri=\"https://report-uri.cloudflare.com/cdn-cgi/beacon/expect-ct\"",
    "etag": "\"2f43c6b080eaedf45f2dec28dbbb295e\"",
    "x-amz-id-2": "sVp6iJ53kKOuAJGm6PGAY7LcBWoK8BNIiMj07ywMbkBP1PXvTqA5yxIrrOzpuAzzyImEVxisKRU=",
    "content-type": "application/typescript; charset=utf-8",
    "cf-request-id": "09acb7b9810000cf108da81000000001",
    "vary": "Accept-Encoding",
    "age": "187405",
    "date": "Sun, 25 Apr 2021 22:20:27 GMT",
    "cf-ray": "645af56f3a5dcf10-IAD",
    "cache-control": "public, max-age=31536000, immutable",
    "x-amz-version-id": "UWeDAXGCWiuGGwfaFhuopOk5eCaPikfn",
    "alt-svc": "h3-27=\":443\"; ma=86400, h3-28=\":443\"; ma=86400, h3-29=\":443\"; ma=86400",
    "cf-cache-status": "HIT"
  },
  "url": "https://deno.land/x/god_crypto@v1.4.9/rsa.ts"
}