{
  "headers": {
    "expect-ct": "max-age=604800, report-uri=\"https://report-uri.cloudflare.com/cdn-cgi/beacon/expect-ct\"",
    "accept-ranges": "bytes",
    "age": "92357",
    "cf-cache-status": "HIT",
    "x-amz-request-id": "K48J6TVRNMZPZE0E",
    "content-type": "application/typescript; charset=utf-8",
    "etag": "\"68427e5c16d3c3c26408b651ae4889e0\"",
    "x-amz-version-id": "lkZt4vAj8XrHE.Q.4CGJincWsmYF.4Pj",
    "cf-request-id": "0a5509add200005a51a4105000000001",
    "vary": "Accept-Encoding",
    "last-modified": "Tue, 13 Apr 2021 22:55:01 GMT",
    "content-length": "325",
    "cf-ray": "6568455c8ac15a51-IAD",
    "date": "Fri, 28 May 2021 14:46:10 GMT",
    "access-control-allow-origin": "*",
    "cache-control": "public, max-age=31536000, immutable",
    "server": "cloudflare",
    "alt-svc": "h3-27=\":443\"; ma=86400, h3-28=\":443\"; ma=86400, h3-29=\":443\"; ma=86400",
    "x-amz-id-2": "E2N1c2AhmmDjduEUG1jbZjz2H1irAywaKnnHdB/HGYvtQ3n36gZye3eC/6268CxWRxrxNrlkQnI="
  },
  "url": "https://deno.land/x/cliffy@v0.18.2/command/types/string.ts"
}