{
  "headers": {
    "accept-ranges": "bytes",
    "x-amz-version-id": ".HqcGYP6HyqvW6NaCfwJAkgHs7LrHG_D",
    "server": "cloudflare",
    "age": "69804",
    "cf-ray": "65f5332ebd25e10e-IAD",
    "alt-svc": "h3-27=\":443\"; ma=86400, h3-28=\":443\"; ma=86400, h3-29=\":443\"; ma=86400, h3=\":443\"; ma=86400",
    "content-length": "4325",
    "etag": "\"2dc22db9b7e2f9df69cce7a0a7c57d2a\"",
    "cf-cache-status": "HIT",
    "x-amz-request-id": "XPEEYM9XMJE3FRD0",
    "expect-ct": "max-age=604800, report-uri=\"https://report-uri.cloudflare.com/cdn-cgi/beacon/expect-ct\"",
    "cf-request-id": "0aad1e51350000e10e3db23000000001",
    "access-control-allow-origin": "*",
    "cache-control": "public, max-age=31536000, immutable",
    "last-modified": "Thu, 27 May 2021 18:29:49 GMT",
    "vary": "Accept-Encoding",
    "x-amz-id-2": "uHLkVHFZ6UXE7YRluaXe6uiUOwDwSpbKFreoXKqSRjtROj24+RqZnKhL17KhDehyu8LT2sy/SXE=",
    "date": "Mon, 14 Jun 2021 17:15:18 GMT",
    "content-type": "application/typescript; charset=utf-8"
  },
  "url": "https://deno.land/x/aws_sdk@v3.17.0-2/middleware-signing/configurations.ts"
}