{
  "headers": {
    "access-control-allow-origin": "*",
    "etag": "\"ca98db0d7e9afcba2d21d041e4b4c45e\"",
    "date": "Wed, 21 Jul 2021 22:11:09 GMT",
    "x-deno-ray": "us-east4-c::62a012a09a1789de27078df45338ff8f",
    "via": "HTTP/1.1 deploy",
    "content-type": "application/typescript; charset=utf-8",
    "expect-ct": "max-age=604800, report-uri=\"https://report-uri.cloudflare.com/cdn-cgi/beacon/expect-ct\"",
    "vary": "Accept-Encoding",
    "server": "cloudflare",
    "x-amz-request-id": "3B1E8G58XP7TFSKP",
    "alt-svc": "h3-27=\":443\"; ma=86400, h3-28=\":443\"; ma=86400, h3-29=\":443\"; ma=86400, h3=\":443\"; ma=86400",
    "x-amz-id-2": "jOJBXoeVnNyigUFd5w7twGuKYY4DPF2LQAz8GTF7zRECwXSB86TLxDzlVAD5SYzPvb5yneMnEtI=",
    "cache-control": "public, max-age=31536000, immutable",
    "content-length": "38",
    "cf-cache-status": "DYNAMIC",
    "x-amz-version-id": ".gA48Yoe30E_auBlXyQXKcrgqtmP3fd.",
    "last-modified": "Mon, 24 May 2021 18:55:08 GMT",
    "cf-ray": "6727c36dfe1c05c6-IAD"
  },
  "url": "https://deno.land/x/aws_sdk@v3.16.0-3/middleware-stack/mod.ts"
}