{
  "headers": {
    "server": "cloudflare",
    "content-length": "1266",
    "cf-ray": "65a4bf1b395b060e-IAD",
    "accept-ranges": "bytes",
    "etag": "\"d3dc8beac225bb8e8003ac45e8617d1e\"",
    "x-amz-id-2": "Zc0+cvmjGyvJWSQHX1Ua2Opx+Dtha2ao9ztHQsPQ2SOcua9JHwZBRFngJy7sckt+D5ihSj4PcJ0=",
    "x-amz-request-id": "AHX9YTRH63230XJW",
    "x-amz-version-id": "Ed5kNotsjl9yYLnBUbUV5DNHb3q7cUuc",
    "cache-control": "public, max-age=31536000, immutable",
    "last-modified": "Sun, 30 May 2021 21:02:22 GMT",
    "vary": "Accept-Encoding",
    "alt-svc": "h3-27=\":443\"; ma=86400, h3-28=\":443\"; ma=86400, h3-29=\":443\"; ma=86400, h3=\":443\"; ma=86400",
    "cf-cache-status": "HIT",
    "age": "213022",
    "content-type": "application/typescript; charset=utf-8",
    "access-control-allow-origin": "*",
    "expect-ct": "max-age=604800, report-uri=\"https://report-uri.cloudflare.com/cdn-cgi/beacon/expect-ct\"",
    "date": "Fri, 04 Jun 2021 22:55:02 GMT",
    "cf-request-id": "0a7ad5c5050000060efa94c000000001"
  },
  "url": "https://deno.land/x/cliffy@v0.19.1/command/completions/mod.ts"
}