{
  "headers": {
    "etag": "\"8c7ea8ec5f06809d27917edef40db04d\"",
    "date": "Sat, 18 Sep 2021 21:04:55 GMT",
    "expect-ct": "max-age=604800, report-uri=\"https://report-uri.cloudflare.com/cdn-cgi/beacon/expect-ct\"",
    "server": "cloudflare",
    "x-amz-version-id": "XACFgUL4X2bifxF4Nlrf8daYZgk1Embv",
    "cf-ray": "690d878b5dc85b94-IAD",
    "alt-svc": "h3=\":443\"; ma=86400, h3-29=\":443\"; ma=86400, h3-28=\":443\"; ma=86400, h3-27=\":443\"; ma=86400",
    "x-amz-id-2": "NA2p+zudnpU1hznza++987vBCW2ob5PnNWm4QbtD3Eid4orh16/9pZOQLk5mL4m3MNICn/v5rCQ=",
    "access-control-allow-origin": "*",
    "x-amz-request-id": "76GACKR1ZJ945XBX",
    "content-type": "application/typescript; charset=utf-8",
    "cache-control": "public, max-age=31536000, immutable",
    "last-modified": "Mon, 19 Jul 2021 09:27:27 GMT",
    "cf-cache-status": "DYNAMIC",
    "connection": "keep-alive",
    "content-length": "667"
  },
  "url": "https://deno.land/x/aws_sdk@v3.22.0-1/querystring-builder/mod.ts"
}