{
  "headers": {
    "cf-ray": "6471de5969324be2-AMS",
    "set-cookie": "__cfduid=dc2dabf988a692e452267455265e8c6101619629454; expires=Fri, 28-May-21 17:04:14 GMT; path=/; domain=.deno.land; HttpOnly; SameSite=Lax; Secure",
    "location": "/x/config_dir@v0.1.1/mod.ts",
    "server": "cloudflare",
    "expect-ct": "max-age=604800, report-uri=\"https://report-uri.cloudflare.com/cdn-cgi/beacon/expect-ct\"",
    "alt-svc": "h3-27=\":443\"; ma=86400, h3-28=\":443\"; ma=86400, h3-29=\":443\"; ma=86400",
    "cf-request-id": "09bb094bed00004be2e52a8000000001",
    "content-length": "0",
    "date": "Wed, 28 Apr 2021 17:04:14 GMT",
    "x-deno-warning": "Implicitly using latest version (v0.1.1) for https://deno.land/x/config_dir/mod.ts",
    "vary": "Accept-Encoding"
  },
  "url": "https://deno.land/x/config_dir/mod.ts"
}