{
  "headers": {
    "x-amz-version-id": "s66pYq399_NRIpQLBtZgTlm.ZRcC2_4z",
    "etag": "\"6012115f37c8f08b951e60d9ab6d087a\"",
    "x-amz-id-2": "st+bPS2gtkpbFcttingS4yc40FijsgXlzundm2M56QnsPJazTnohFTEuTV3GzXa78fHWV2GmigY=",
    "cf-ray": "65f533322a9ce10e-IAD",
    "content-length": "1338",
    "x-amz-request-id": "P7J1PVMRGP9ZQEG4",
    "alt-svc": "h3-27=\":443\"; ma=86400, h3-28=\":443\"; ma=86400, h3-29=\":443\"; ma=86400, h3=\":443\"; ma=86400",
    "vary": "Accept-Encoding",
    "cache-control": "public, max-age=31536000, immutable",
    "server": "cloudflare",
    "accept-ranges": "bytes",
    "age": "69804",
    "cf-cache-status": "HIT",
    "date": "Mon, 14 Jun 2021 17:15:18 GMT",
    "expect-ct": "max-age=604800, report-uri=\"https://report-uri.cloudflare.com/cdn-cgi/beacon/expect-ct\"",
    "cf-request-id": "0aad1e535c0000e10e1799d000000001",
    "last-modified": "Thu, 27 May 2021 18:29:49 GMT",
    "access-control-allow-origin": "*",
    "content-type": "application/typescript; charset=utf-8"
  },
  "url": "https://deno.land/x/aws_sdk@v3.17.0-2/middleware-stack/types.ts"
}