{
  "headers": {
    "cache-control": "public, max-age=31536000, immutable",
    "etag": "\"2ae6779da93c93a83466f9d6a0afc2b3\"",
    "access-control-allow-origin": "*",
    "x-amz-version-id": "1FIAA7TsKWBAQzUzn0k9UZjBe6MsHkuV",
    "expect-ct": "max-age=604800, report-uri=\"https://report-uri.cloudflare.com/cdn-cgi/beacon/expect-ct\"",
    "vary": "Accept-Encoding",
    "accept-ranges": "bytes",
    "server": "cloudflare",
    "date": "Sat, 29 May 2021 16:07:22 GMT",
    "x-amz-id-2": "bNc4Gl9iWRjcNOPfrVN9JebR7AVHMGVTSrNdNfp7RBVQsG4ENfE7WuRP30hD8Uhi5Pu15rPUUYc=",
    "content-type": "application/typescript; charset=utf-8",
    "age": "91271",
    "content-length": "1645",
    "cf-ray": "6570f9ab4e3d5a88-IAD",
    "cf-cache-status": "HIT",
    "x-amz-request-id": "KCFKK1P5S1S1N5GN",
    "cf-request-id": "0a5a7a5f1600005a8850800000000001",
    "last-modified": "Mon, 24 May 2021 18:55:08 GMT",
    "alt-svc": "h3-27=\":443\"; ma=86400, h3-28=\":443\"; ma=86400, h3-29=\":443\"; ma=86400"
  },
  "url": "https://deno.land/x/aws_sdk@v3.16.0-3/types/client.ts"
}