{
  "headers": {
    "x-amz-version-id": "qW8JshK9nY0q8W6s326pNUwgStaH_pIw",
    "x-amz-request-id": "5NGW7TSD98AAX3QS",
    "access-control-allow-origin": "*",
    "accept-ranges": "bytes",
    "cache-control": "public, max-age=31536000, immutable",
    "x-amz-id-2": "tQAFDmNYPy8lUTQnSsy6uGUPgWJGirrhRpjCS9WTZx7I0dA/NugyMvLx6Gqq3qdCc6Xzqr/Hc9A=",
    "cf-cache-status": "MISS",
    "vary": "Accept-Encoding",
    "cf-ray": "65a4bf227efe060e-IAD",
    "server": "cloudflare",
    "last-modified": "Mon, 24 May 2021 18:55:05 GMT",
    "date": "Fri, 04 Jun 2021 22:55:04 GMT",
    "cf-request-id": "0a7ad5c9990000060ec5a4d000000001",
    "content-length": "3868",
    "alt-svc": "h3-27=\":443\"; ma=86400, h3-28=\":443\"; ma=86400, h3-29=\":443\"; ma=86400, h3=\":443\"; ma=86400",
    "etag": "\"baf7c30910de5bd992a03ea8c864d753\"",
    "content-type": "application/typescript; charset=utf-8",
    "expect-ct": "max-age=604800, report-uri=\"https://report-uri.cloudflare.com/cdn-cgi/beacon/expect-ct\""
  },
  "url": "https://deno.land/x/aws_sdk@v3.16.0-3/client-sso/commands/ListAccountsCommand.ts"
}