{
  "headers": {
    "cache-control": "public, max-age=31536000, immutable",
    "etag": "\"4de77229493348a2a97a9b8ffe2d2c2e\"",
    "content-type": "application/typescript; charset=utf-8",
    "content-length": "9390",
    "access-control-allow-origin": "*",
    "x-amz-id-2": "pgEOCGykvUaAm+sh0PC+0K4jjty9pS+mZh+vwyJcLXiU0sq9/95wAHEas+yXGgpzE5eg85KWL2w=",
    "date": "Wed, 08 Sep 2021 21:32:50 GMT",
    "x-amz-version-id": "LUQTHxOaWaGZdtvQKPAE57lI1_OYvKNg",
    "last-modified": "Mon, 19 Jul 2021 09:27:21 GMT",
    "x-amz-request-id": "G4027Z5CMPTZQZZZ",
    "server": "deploy/us-east4-c"
  },
  "url": "https://deno.land/x/aws_sdk@v3.22.0-1/client-s3/commands/HeadObjectCommand.ts"
}