{
  "headers": {
    "cache-control": "public, max-age=31536000, immutable",
    "access-control-allow-origin": "*",
    "content-type": "application/typescript; charset=utf-8",
    "date": "Fri, 20 Aug 2021 15:10:14 GMT",
    "last-modified": "Mon, 19 Jul 2021 09:27:21 GMT",
    "server": "AmazonS3",
    "x-amz-id-2": "5jP5N5jkYCKHn4Z04o2QMbciO3rAb6jSzDag//ngNYfA31DK3CSUqUJIg512h9PTvpMo9eEJBkM=",
    "content-length": "1575",
    "x-amz-request-id": "7PWCMY600NB60NJE",
    "etag": "\"fae7168c0877d1d98cf91da1c76cb57a\"",
    "x-amz-version-id": "D528NZ2bR0qnlYYi.6RQ0AnL9v.7IuLg"
  },
  "url": "https://deno.land/x/aws_sdk@v3.22.0-1/client-s3/waiters/waitForBucketNotExists.ts"
}