{
  "headers": {
    "access-control-allow-origin": "*",
    "last-modified": "Mon, 12 Jul 2021 23:47:14 GMT",
    "etag": "\"52815b81b01af1a1e53eacd19484664a\"",
    "content-type": "application/typescript; charset=utf-8",
    "date": "Wed, 08 Sep 2021 21:32:50 GMT",
    "x-amz-version-id": "EU7Dkza7t6P4ZafW.IKt2hrpp498apLc",
    "content-length": "897",
    "cache-control": "public, max-age=31536000, immutable",
    "x-amz-id-2": "FOy0yy49Uh9xV6HDRI0DfDyuva9phJfF9KR+ER7GyLdOE3kk2pKVWal/JzWOit1+yLz4fsvnPqE=",
    "x-amz-request-id": "G406JWZ6H681A4PS",
    "server": "deploy/us-east4-c"
  },
  "url": "https://deno.land/std@0.101.0/node/_fs/_fs_truncate.ts"
}