{
  "headers": {
    "vary": "Accept-Encoding",
    "x-amz-version-id": "7iVckInSX.DjhkNxVT7BxqBIG_7YXcmy",
    "expect-ct": "max-age=604800, report-uri=\"https://report-uri.cloudflare.com/cdn-cgi/beacon/expect-ct\"",
    "content-length": "1652",
    "cache-control": "public, max-age=31536000, immutable",
    "cf-request-id": "0a553fcb5c00005c9bc89d6000000001",
    "last-modified": "Mon, 24 May 2021 18:55:08 GMT",
    "accept-ranges": "bytes",
    "server": "cloudflare",
    "etag": "\"b027f784ec56b37a8558f35b3c4306a2\"",
    "content-type": "application/typescript; charset=utf-8",
    "x-amz-id-2": "YnRAR2JPVD/VNoD9KUnLM0xN8T1P6Wf/rMXEDbeQYskRsVZVTfy2JJZUsWsQZQ5Le/svlOe1RnQ=",
    "cf-ray": "65689bf21ad05c9b-IAD",
    "access-control-allow-origin": "*",
    "x-amz-request-id": "CZ8KEEQQATTXX700",
    "date": "Fri, 28 May 2021 15:45:17 GMT",
    "cf-cache-status": "MISS",
    "alt-svc": "h3-27=\":443\"; ma=86400, h3-28=\":443\"; ma=86400, h3-29=\":443\"; ma=86400"
  },
  "url": "https://deno.land/x/aws_sdk@v3.16.0-3/smithy-client/lazy-json.ts"
}