{
  "headers": {
    "x-amz-request-id": "7PW44710433E9BDV",
    "content-type": "application/typescript; charset=utf-8",
    "date": "Fri, 20 Aug 2021 15:10:14 GMT",
    "last-modified": "Thu, 12 Aug 2021 20:51:13 GMT",
    "server": "AmazonS3",
    "content-length": "5911",
    "x-amz-id-2": "I2DKSodXrP6X3MYvgc5396i9Km0ARlSbDcsg0etgIKKmakxm5awVRt96jjcab80qTcpHqClPtHo=",
    "etag": "\"1814b4d845d4436ad04872b13ade9265\"",
    "cache-control": "public, max-age=31536000, immutable",
    "access-control-allow-origin": "*",
    "x-amz-version-id": "MGi6LzNuweOgV4pBiXJDpSfKwUH08EYC"
  },
  "url": "https://deno.land/x/cliffy@v0.19.5/command/_errors.ts"
}