{
  "headers": {
    "alt-svc": "h3-27=\":443\"; ma=86400, h3-28=\":443\"; ma=86400, h3-29=\":443\"; ma=86400",
    "date": "Wed, 28 Apr 2021 17:04:15 GMT",
    "x-amz-id-2": "N1/+UWTYd8lWv2VLuumEK2JlUM0g8szS2LWNWhu8oLPl5zPnf/97m5fbERfEl2MXjh2JosU0bQw=",
    "x-amz-request-id": "NBF2N86DMQGYCHV6",
    "server": "cloudflare",
    "cf-ray": "6471de5e5e4a4be2-AMS",
    "content-length": "679",
    "content-type": "application/typescript; charset=utf-8",
    "expect-ct": "max-age=604800, report-uri=\"https://report-uri.cloudflare.com/cdn-cgi/beacon/expect-ct\"",
    "last-modified": "Tue, 13 Apr 2021 22:55:01 GMT",
    "access-control-allow-origin": "*",
    "vary": "Accept-Encoding",
    "set-cookie": "__cfduid=d1db0dddecf96e5b110e6464ebbb1af0e1619629455; expires=Fri, 28-May-21 17:04:15 GMT; path=/; domain=.deno.land; HttpOnly; SameSite=Lax; Secure",
    "etag": "\"adefbdaab9b90ec00d3e7daf721b6895\"",
    "cf-request-id": "09bb094ef500004be2c1993000000001",
    "x-amz-version-id": "AV2jJbckjiYN5HKpUylh5zCnKywEl3ts",
    "accept-ranges": "bytes",
    "age": "99139",
    "cache-control": "public, max-age=31536000, immutable",
    "cf-cache-status": "HIT"
  },
  "url": "https://deno.land/x/cliffy@v0.18.2/table/border.ts"
}