{
  "headers": {
    "cf-cache-status": "DYNAMIC",
    "alt-svc": "h3-27=\":443\"; ma=86400, h3-28=\":443\"; ma=86400, h3-29=\":443\"; ma=86400, h3=\":443\"; ma=86400",
    "cache-control": "public, max-age=31536000, immutable",
    "content-type": "application/typescript; charset=utf-8",
    "x-amz-request-id": "3B18V47NKK9ESP14",
    "x-deno-ray": "us-east4-c::6c99ab3c9d5cc1e41543e3e907d2ebe1",
    "etag": "\"d942628e8e1de54085297aeda893a1ad\"",
    "via": "HTTP/1.1 deploy",
    "access-control-allow-origin": "*",
    "content-length": "15026",
    "date": "Wed, 21 Jul 2021 22:11:09 GMT",
    "x-amz-id-2": "mnEi78r+1BBeIwJ2BNhuWcLQ/wO7C2bO5Ts3MHPPCon/l/4AfFEzaoVjmxqukGT1szXTOrwrJak=",
    "x-amz-version-id": "ccBrQcLTmFa9P2EDPz5ZJoroWPn9oTFF",
    "expect-ct": "max-age=604800, report-uri=\"https://report-uri.cloudflare.com/cdn-cgi/beacon/expect-ct\"",
    "last-modified": "Mon, 24 May 2021 18:55:05 GMT",
    "vary": "Accept-Encoding",
    "server": "cloudflare",
    "cf-ray": "6727c36fba6e05c6-IAD"
  },
  "url": "https://deno.land/x/aws_sdk@v3.16.0-3/client-sts/commands/AssumeRoleWithWebIdentityCommand.ts"
}