{
  "headers": {
    "cf-ray": "65a4bf20db68060e-IAD",
    "accept-ranges": "bytes",
    "etag": "\"d942628e8e1de54085297aeda893a1ad\"",
    "alt-svc": "h3-27=\":443\"; ma=86400, h3-28=\":443\"; ma=86400, h3-29=\":443\"; ma=86400, h3=\":443\"; ma=86400",
    "expect-ct": "max-age=604800, report-uri=\"https://report-uri.cloudflare.com/cdn-cgi/beacon/expect-ct\"",
    "date": "Fri, 04 Jun 2021 22:55:03 GMT",
    "content-length": "15026",
    "x-amz-version-id": "ccBrQcLTmFa9P2EDPz5ZJoroWPn9oTFF",
    "x-amz-id-2": "E9Viiws8z9rJhLRUPohVdwlHjmhJwrXqHKXGdjZ2G0LXzjS/4uNjaKfGcWIXGXBMBvei3E00cSg=",
    "cf-cache-status": "MISS",
    "x-amz-request-id": "BPZ52SP0NR9TCV0Z",
    "access-control-allow-origin": "*",
    "content-type": "application/typescript; charset=utf-8",
    "last-modified": "Mon, 24 May 2021 18:55:05 GMT",
    "cache-control": "public, max-age=31536000, immutable",
    "cf-request-id": "0a7ad5c8870000060efeb7e000000001",
    "vary": "Accept-Encoding",
    "server": "cloudflare"
  },
  "url": "https://deno.land/x/aws_sdk@v3.16.0-3/client-sts/commands/AssumeRoleWithWebIdentityCommand.ts"
}