{
  "headers": {
    "expect-ct": "max-age=604800, report-uri=\"https://report-uri.cloudflare.com/cdn-cgi/beacon/expect-ct\"",
    "vary": "Accept-Encoding",
    "cf-request-id": "0a553fcb5700005c9bcabce000000001",
    "server": "cloudflare",
    "access-control-allow-origin": "*",
    "content-length": "1497",
    "cf-ray": "65689bf21acb5c9b-IAD",
    "etag": "\"a59555d4ee88e36d2368d1c790e2c7ab\"",
    "x-amz-request-id": "CZ8H7HNMA3JKW289",
    "content-type": "application/typescript; charset=utf-8",
    "cf-cache-status": "MISS",
    "date": "Fri, 28 May 2021 15:45:17 GMT",
    "last-modified": "Mon, 24 May 2021 18:55:08 GMT",
    "x-amz-id-2": "ejaFOHrgb+EYtASMuFF8PoX/AVrHLa7f8cZjqSdAqBNfhbGk4zzjde/hhNd6OD3vZ3ZukywCj5U=",
    "alt-svc": "h3-27=\":443\"; ma=86400, h3-28=\":443\"; ma=86400, h3-29=\":443\"; ma=86400",
    "accept-ranges": "bytes",
    "cache-control": "public, max-age=31536000, immutable",
    "x-amz-version-id": "8tN7AJHwVrOXzMn.Q9WQgv1Bsnxn63Gf"
  },
  "url": "https://deno.land/x/aws_sdk@v3.16.0-3/smithy-client/split-every.ts"
}