{
  "headers": {
    "x-amz-request-id": "G405M6Q90PGWJ1XY",
    "server": "deploy/us-east4-c",
    "etag": "\"f42f4330ef0d1f4834df6802fcf1656c\"",
    "x-amz-id-2": "4oTnkY8cWBbdkj8brRRkB3zpoUhveW2BTvutbo+WRV/SMl2r5RbRRhsObjp9QytQ/7mv2SzuaMg=",
    "last-modified": "Mon, 19 Jul 2021 09:27:27 GMT",
    "content-type": "application/typescript; charset=utf-8",
    "date": "Wed, 08 Sep 2021 21:32:50 GMT",
    "cache-control": "public, max-age=31536000, immutable",
    "x-amz-version-id": ".0HZ_gecaii3xpqSscUx2kuWyF0Fab8l",
    "access-control-allow-origin": "*",
    "content-length": "4051"
  },
  "url": "https://deno.land/x/aws_sdk@v3.22.0-1/middleware-bucket-endpoint/bucketEndpointMiddleware.ts"
}