{
  "headers": {
    "last-modified": "Mon, 19 Jul 2021 09:27:21 GMT",
    "access-control-allow-origin": "*",
    "server": "AmazonS3",
    "content-length": "538286",
    "etag": "\"3eff0a558002f1b1e144d8f4939b97aa\"",
    "date": "Fri, 20 Aug 2021 15:10:14 GMT",
    "content-type": "application/typescript; charset=utf-8",
    "x-amz-id-2": "EywtGNo1e75a6f9L6r0FLfl0g1m1/2/MLTfGBo+keR8yzcTdDuwj+cGmE/3tbwQOHMPDzdhHwrA=",
    "x-amz-version-id": "YHug0_AUx8YCJOg6QfQqXXtYeFvReYmc",
    "cache-control": "public, max-age=31536000, immutable",
    "x-amz-request-id": "7PWC6MNJAWVD44DK"
  },
  "url": "https://deno.land/x/aws_sdk@v3.22.0-1/client-s3/protocols/Aws_restXml.ts"
}