{
  "headers": {
    "x-amz-request-id": "6AGK01PR857GYQBX",
    "etag": "\"b2b73b5653f9eeaabece5bee6764a60c\"",
    "last-modified": "Sat, 23 Jan 2021 01:23:53 GMT",
    "x-amz-version-id": "8GZUSmCjHSSzBYWa41cKQQyWzxIGlJr9",
    "accept-ranges": "bytes",
    "x-amz-id-2": "cj72Ab3+SbM36/hscfZnsu65RR1U09u74DuIHKct3coiFoHSiDlpLcChaDW8mF333eFF6p8A1P4=",
    "content-type": "application/typescript; charset=utf-8",
    "access-control-allow-origin": "*",
    "date": "Mon, 14 Jun 2021 16:50:37 GMT",
    "cf-request-id": "0aad07b90400005c237518b000000001",
    "server": "cloudflare",
    "expect-ct": "max-age=604800, report-uri=\"https://report-uri.cloudflare.com/cdn-cgi/beacon/expect-ct\"",
    "age": "399990",
    "vary": "Accept-Encoding",
    "cf-ray": "65f50f080be55c23-IAD",
    "cache-control": "public, max-age=31536000, immutable",
    "content-length": "267",
    "alt-svc": "h3-27=\":443\"; ma=86400, h3-28=\":443\"; ma=86400, h3-29=\":443\"; ma=86400, h3=\":443\"; ma=86400",
    "cf-cache-status": "HIT"
  },
  "url": "https://deno.land/x/god_crypto@v1.4.9/src/math.ts"
}