{
  "headers": {
    "last-modified": "Mon, 24 May 2021 18:55:02 GMT",
    "x-amz-id-2": "kl19yilUgV/IXT57ohsYa18OmUm8aZ4sK7rCpF4I66CYsabLzVVZ9bzS9Js/mvFJbASOF3W2IcA=",
    "access-control-allow-origin": "*",
    "alt-svc": "h3-27=\":443\"; ma=86400, h3-28=\":443\"; ma=86400, h3-29=\":443\"; ma=86400",
    "accept-ranges": "bytes",
    "cf-request-id": "0a553fcaba00005c9bc89c2000000001",
    "date": "Fri, 28 May 2021 15:45:17 GMT",
    "cf-cache-status": "MISS",
    "vary": "Accept-Encoding",
    "expect-ct": "max-age=604800, report-uri=\"https://report-uri.cloudflare.com/cdn-cgi/beacon/expect-ct\"",
    "etag": "\"14d63a4dae92e1fc6758e6c14571ceac\"",
    "cache-control": "public, max-age=31536000, immutable",
    "x-amz-request-id": "TCSV3FC0GVRZKDT7",
    "server": "cloudflare",
    "content-type": "application/typescript; charset=utf-8",
    "content-length": "404912",
    "x-amz-version-id": "oZYbVKDJ0eh2UpipCYsdF5qhy7JTfjbM",
    "cf-ray": "65689bf1291e5c9b-IAD"
  },
  "url": "https://deno.land/x/aws_sdk@v3.16.0-3/client-s3/models/models_0.ts"
}